{
    "images": [
        {
            "height": 1440,
            "width": 1920,
            "id": 0,
            "file_name": "cars-with-license-plates_121.jpeg"
        },
        {
            "height": 533,
            "width": 800,
            "id": 1,
            "file_name": "cars-with-license-plates_13b.jpeg"
        },
        {
            "height": 742,
            "width": 1200,
            "id": 2,
            "file_name": "cars-with-license-plates_1af.jpeg"
        },
        {
            "height": 297,
            "width": 445,
            "id": 3,
            "file_name": "cars-with-license-plates_1bc.jpeg"
        },
        {
            "height": 597,
            "width": 1062,
            "id": 4,
            "file_name": "cars-with-license-plates_1dd.jpeg"
        },
        {
            "height": 768,
            "width": 1160,
            "id": 5,
            "file_name": "cars-with-license-plates_243.jpeg"
        },
        {
            "height": 600,
            "width": 900,
            "id": 6,
            "file_name": "cars-with-license-plates_249.jpeg"
        },
        {
            "height": 720,
            "width": 1280,
            "id": 7,
            "file_name": "cars-with-license-plates_268.jpeg"
        },
        {
            "height": 1349,
            "width": 2399,
            "id": 8,
            "file_name": "cars-with-license-plates_290.jpeg"
        },
        {
            "height": 768,
            "width": 1024,
            "id": 9,
            "file_name": "cars-with-license-plates_301.jpeg"
        },
        {
            "height": 347,
            "width": 521,
            "id": 10,
            "file_name": "cars-with-license-plates_364.jpeg"
        },
        {
            "height": 683,
            "width": 1024,
            "id": 11,
            "file_name": "cars-with-license-plates_369.jpeg"
        }
    ],
    "categories": [
        {
            "supercategory": "license",
            "id": 0,
            "name": "license"
        }
    ],
    "annotations": [
        {
            "segmentation": [
                [
                    289.10447761194035,
                    531.9402985074627,
                    966.7164179104477,
                    522.9850746268658,
                    989.1044776119402,
                    545.3731343283582,
                    999.5522388059701,
                    834.9253731343284,
                    984.6268656716418,
                    848.3582089552239,
                    327.9104477611941,
                    908.0597014925373,
                    305.52238805970154,
                    896.1194029850747
                ]
            ],
            "iscrowd": 0,
            "area": 244630.20717308973,
            "image_id": 0,
            "bbox": [
                289.0,
                522.0,
                710.0,
                386.0
            ],
            "category_id": 0,
            "id": 1
        },
        {
            "segmentation": [
                [
                    342.032967032967,
                    243.97252747252747,
                    461.26373626373623,
                    243.42307692307693,
                    460.71428571428567,
                    300.0164835164835,
                    340.38461538461536,
                    300.5659340659341
                ]
            ],
            "iscrowd": 0,
            "area": 6778.166888056992,
            "image_id": 1,
            "bbox": [
                340.0,
                243.0,
                121.0,
                57.0
            ],
            "category_id": 0,
            "id": 2
        },
        {
            "segmentation": [
                [
                    457.63358778625957,
                    333.5954198473283,
                    704.9618320610687,
                    335.1221374045802,
                    704.1984732824427,
                    389.3206106870229,
                    456.10687022900765,
                    387.793893129771
                ]
            ],
            "iscrowd": 0,
            "area": 13427.247829380503,
            "image_id": 2,
            "bbox": [
                456.0,
                333.0,
                248.0,
                56.0
            ],
            "category_id": 0,
            "id": 3
        },
        {
            "segmentation": [
                [
                    76.47553516819573,
                    68.37767584097861,
                    84.73241590214069,
                    62.8730886850153,
                    359.0443425076453,
                    62.8730886850153,
                    370.97094801223244,
                    70.51834862385323,
                    370.0535168195719,
                    201.4051987767584,
                    363.63149847094803,
                    210.2737003058104,
                    358.12691131498474,
                    211.80275229357798,
                    212.56116207951072,
                    207.21559633027522,
                    82.89755351681958,
                    208.7446483180428,
                    73.41743119266056,
                    202.01681957186545
                ]
            ],
            "iscrowd": 0,
            "area": 43022.56637581947,
            "image_id": 3,
            "bbox": [
                73.0,
                62.0,
                297.0,
                149.0
            ],
            "category_id": 0,
            "id": 4
        },
        {
            "segmentation": [
                [
                    462.0,
                    218.5,
                    602.0,
                    218.5,
                    601.3333333333334,
                    285.8333333333333,
                    589.3333333333334,
                    289.16666666666663,
                    459.3333333333333,
                    286.5
                ]
            ],
            "iscrowd": 0,
            "area": 9773.111111111066,
            "image_id": 4,
            "bbox": [
                459.0,
                218.0,
                143.0,
                71.0
            ],
            "category_id": 0,
            "id": 5
        },
        {
            "segmentation": [
                [
                    188.3333333333333,
                    195.11111111111114,
                    203.41269841269835,
                    170.50793650793653,
                    802.6190476190476,
                    170.50793650793653,
                    824.8412698412699,
                    180.82539682539687,
                    838.3333333333333,
                    198.2857142857143,
                    828.015873015873,
                    474.4761904761905,
                    812.936507936508,
                    492.73015873015873,
                    221.6666666666666,
                    503.8412698412698,
                    197.8571428571428,
                    489.55555555555554,
                    190.71428571428567,
                    467.3333333333333
                ]
            ],
            "iscrowd": 0,
            "area": 210029.2894935751,
            "image_id": 5,
            "bbox": [
                188.0,
                170.0,
                650.0,
                333.0
            ],
            "category_id": 0,
            "id": 6
        },
        {
            "segmentation": [
                [
                    370.679012345679,
                    258.0246913580247,
                    555.8641975308642,
                    259.87654320987656,
                    558.9506172839506,
                    268.51851851851853,
                    554.0123456790124,
                    361.7283950617284,
                    371.91358024691357,
                    359.87654320987656,
                    368.2098765432099,
                    349.38271604938274
                ]
            ],
            "iscrowd": 0,
            "area": 19052.164304221922,
            "image_id": 6,
            "bbox": [
                368.0,
                258.0,
                190.0,
                103.0
            ],
            "category_id": 0,
            "id": 7
        },
        {
            "segmentation": [
                [
                    515.4032258064516,
                    200.32258064516128,
                    780.7258064516129,
                    242.25806451612902,
                    758.9516129032259,
                    380.16129032258067,
                    505.7258064516129,
                    327.741935483871,
                    496.0483870967742,
                    315.64516129032256
                ]
            ],
            "iscrowd": 0,
            "area": 35812.63007284084,
            "image_id": 7,
            "bbox": [
                496.0,
                200.0,
                284.0,
                180.0
            ],
            "category_id": 0,
            "id": 8
        },
        {
            "segmentation": [
                [
                    733.5909090909091,
                    472.9848484848485,
                    718.439393939394,
                    860.8636363636364,
                    729.0454545454546,
                    882.0757575757575,
                    1429.0454545454545,
                    1027.530303030303,
                    1460.8636363636363,
                    1013.8939393939394,
                    1474.5,
                    983.5909090909091,
                    1494.1969696969697,
                    586.6212121212121
                ]
            ],
            "iscrowd": 0,
            "area": 326089.30211202893,
            "image_id": 8,
            "bbox": [
                718.0,
                472.0,
                776.0,
                555.0
            ],
            "category_id": 0,
            "id": 9
        },
        {
            "segmentation": [
                [
                    184.6190476190476,
                    218.92063492063494,
                    185.41269841269838,
                    484.7936507936508,
                    202.07936507936506,
                    503.04761904761904,
                    233.8253968253968,
                    507.015873015873,
                    782.2380952380952,
                    512.5714285714286,
                    800.4920634920635,
                    491.93650793650795,
                    807.6349206349206,
                    469.7142857142857,
                    807.6349206349206,
                    226.8571428571429
                ]
            ],
            "iscrowd": 0,
            "area": 177860.60720584518,
            "image_id": 9,
            "bbox": [
                184.0,
                218.0,
                623.0,
                294.0
            ],
            "category_id": 0,
            "id": 10
        },
        {
            "segmentation": [
                [
                    226.39285714285717,
                    212.07142857142856,
                    323.5357142857143,
                    211.35714285714286,
                    327.10714285714283,
                    216.0,
                    326.3928571428571,
                    256.3571428571429,
                    322.10714285714283,
                    259.5714285714286,
                    229.6071428571429,
                    259.5714285714286,
                    226.0357142857143,
                    256.7142857142857
                ]
            ],
            "iscrowd": 0,
            "area": 4793.176020408195,
            "image_id": 10,
            "bbox": [
                226.0,
                211.0,
                101.0,
                48.0
            ],
            "category_id": 0,
            "id": 11
        },
        {
            "segmentation": [
                [
                    346.85915492957747,
                    266.1478873239436,
                    357.4225352112676,
                    255.5845070422535,
                    625.0281690140845,
                    293.612676056338,
                    637.0,
                    300.65492957746477,
                    644.7464788732394,
                    314.7394366197183,
                    627.1408450704225,
                    449.2464788732394,
                    616.5774647887324,
                    454.8802816901408,
                    594.7464788732394,
                    452.7676056338028,
                    334.88732394366195,
                    411.9225352112676,
                    329.2535211267605,
                    402.7676056338028,
                    326.4366197183098,
                    388.68309859154925
                ]
            ],
            "iscrowd": 0,
            "area": 48299.196587978746,
            "image_id": 11,
            "bbox": [
                326.0,
                255.0,
                318.0,
                199.0
            ],
            "category_id": 0,
            "id": 12
        }
    ]
}